mylib053/__init__.py
mylib053-0.1.dist-info/LICENSE.txt
mylib053-0.1.dist-info/METADATA
mylib053-0.1.dist-info/WHEEL
mylib053-0.1.dist-info/top_level.txt
mylib053-0.1.dist-info/RECORD
