Metadata-Version: 2.1
Name: mylib053
Version: 0.1
Summary: for calculating cube
Author: Vivek
Author-email: vivekhalpatrao96k@gmail.com
Classifier: Programming Language :: Python :: 3
Classifier: License :: OSI Approved :: MIT License
Classifier: Operating System :: OS Independent
License-File: LICENSE.txt
